<?xml version="1.0" encoding="UTF-8"?>
<objects serializationModel="Studio.02.00.00">
	<object class="ParameterPreset" id="{5cfcde34-bbf2-4479-ac27-593c0fe7abea}">
		<property name="name">
			<value>General Fade Out</value>
		</property>
		<relationship name="folder">
			<destination>{d775167c-1d8a-4051-85b1-0b363308684f}</destination>
		</relationship>
		<relationship name="parameter">
			<destination>{6603ac2d-f91f-40a0-82ad-24252026372a}</destination>
		</relationship>
	</object>
	<object class="GameParameter" id="{6603ac2d-f91f-40a0-82ad-24252026372a}">
		<property name="initialValue">
			<value>0</value>
		</property>
		<property name="seekSpeed">
			<value>0.50000005960464478</value>
		</property>
	</object>
</objects>
